mcp_server_las/__init__.py
mcp_server_las/config.py
mcp_server_las/las_service.py
mcp_server_las/server.py
mcp_server_las/serverRemote.py
mcp_server_las/serverSse.py
las_mcp_server-0.1.0.dist-info/METADATA
las_mcp_server-0.1.0.dist-info/WHEEL
las_mcp_server-0.1.0.dist-info/entry_points.txt
las_mcp_server-0.1.0.dist-info/top_level.txt
las_mcp_server-0.1.0.dist-info/RECORD
