Metadata-Version: 2.4
Name: las-mcp-server
Version: 0.1.0
Summary: Add your description here
Requires-Python: >=3.13
Requires-Dist: httpx>=0.28.1
Requires-Dist: volcengine>=1.0.175
Requires-Dist: mcp[cli]>=1.6.0
